{"nodes": [{"id": "mentions_legales_page", "label": "Mentions L\u00e9gales Page", "file_type": "document", "source_file": "mentions-legales.html", "source_location": "h1", "source_url": null, "captured_at": null, "author": null, "contributor": null}, {"id": "mentions_vercel_hosting", "label": "Vercel Inc. (Hosting Provider)", "file_type": "document", "source_file": "mentions-legales.html", "source_location": "section:nth-child(2)", "source_url": "https://vercel.com", "captured_at": null, "author": null, "contributor": null}, {"id": "mentions_propriete_intellectuelle", "label": "Intellectual Property Clause", "file_type": "document", "source_file": "mentions-legales.html", "source_location": "section:nth-child(3)", "source_url": null, "captured_at": null, "author": null, "contributor": null}, {"id": "mentions_droit_francais", "label": "French Law Jurisdiction", "file_type": "document", "source_file": "mentions-legales.html", "source_location": "section:nth-child(6)", "source_url": null, "captured_at": null, "author": null, "contributor": null}], "edges": [{"source": "mentions_legales_page", "target": "mentions_vercel_hosting", "relation": "references", "confidence": "EXTRACTED", "confidence_score": 1.0, "source_file": "mentions-legales.html", "source_location": "section:nth-child(2)", "weight": 1.0}, {"source": "mentions_legales_page", "target": "mentions_droit_francais", "relation": "implements", "confidence": "EXTRACTED", "confidence_score": 1.0, "source_file": "mentions-legales.html", "source_location": "section:nth-child(6)", "weight": 1.0}, {"source": "mentions_legales_page", "target": "mentions_propriete_intellectuelle", "relation": "references", "confidence": "EXTRACTED", "confidence_score": 1.0, "source_file": "mentions-legales.html", "source_location": "section:nth-child(3)", "weight": 1.0}, {"source": "index_abdallah_ait_essaghir", "target": "mentions_legales_page", "relation": "references", "confidence": "EXTRACTED", "confidence_score": 1.0, "source_file": "mentions-legales.html", "source_location": "Repr\u00e9sentant l\u00e9gal", "weight": 1.0}, {"source": "politique_conf_rgpd", "target": "mentions_droit_francais", "relation": "conceptually_related_to", "confidence": "INFERRED", "confidence_score": 0.75, "source_file": "mentions-legales.html", "source_location": "section:nth-child(6)", "weight": 0.75}], "hyperedges": [{"id": "abema_legal_compliance_cluster", "label": "Legal & Compliance Cluster", "nodes": ["mentions_legales_page", "politique_conf_page", "politique_conf_rgpd", "mentions_droit_francais"], "relation": "form", "confidence": "EXTRACTED", "confidence_score": 0.92, "source_file": "mentions-legales.html"}]}